{
  "environment": "web",
  "format": "html",
  "prefix": "https://storage.googleapis.com",
  "mainga": "UA-49880327-14",
  "updated": "2021-04-09T15:28:26Z",
  "id": "aprendizado-maquina",
  "duration": 0,
  "title": "Introdução à Aprendizado de Máquina",
  "summary": "Introdução à Aprendizado de Máquina",
  "source": "codelabs/aprendizado-maquina/codelab.md",
  "theme": "",
  "status": [
    "published"
  ],
  "category": [
    "platiagro"
  ],
  "tags": [
    "web"
  ],
  "feedback": "https://github.com/platiagro/tutorials",
  "url": "aprendizado-maquina"
}
